server/__init__.py
server/decorators.py
server/metaclasses.py
server/server.py
server/server_database.py
server/common/__init__.py
server/common/utils.py
server/common/variables.py
mess_server_eTcilopp-0.5.2.dist-info/METADATA
mess_server_eTcilopp-0.5.2.dist-info/WHEEL
mess_server_eTcilopp-0.5.2.dist-info/top_level.txt
mess_server_eTcilopp-0.5.2.dist-info/RECORD
