Metadata-Version: 2.1
Name: mess-server-eTcilopp
Version: 0.5.2
Summary: Messenger - server
Home-page: UNKNOWN
Author: Alexander Kirikeza
Author-email: kirikeza@mail.ru
License: UNKNOWN
Platform: UNKNOWN
Requires-Dist: PyQt5
Requires-Dist: sqlalchemy
Requires-Dist: pycryptodome
Requires-Dist: pycryptodomex
